MANIFEST.in
Makefile
NEWS.txt
README.txt
bootstrap.py
conf.py
contact.txt
distribute_setup.py
gnu-COPYING-GPL
index.txt
setup.cfg
setup.py
setup_helpers.py
template.py
doc/index.txt
doc/authors/index.txt
doc/backends/index.txt
pkgme/__init__.py
pkgme/api.py
pkgme/backend.py
pkgme/debuild.py
pkgme/errors.py
pkgme/info_elements.py
pkgme/package_files.py
pkgme/project_info.py
pkgme/rstinfo.py
pkgme/run_script.py
pkgme/template_file.py
pkgme/testing.py
pkgme/trace.py
pkgme/upload.py
pkgme/write.py
pkgme.egg-info/PKG-INFO
pkgme.egg-info/SOURCES.txt
pkgme.egg-info/dependency_links.txt
pkgme.egg-info/entry_points.txt
pkgme.egg-info/requires.txt
pkgme.egg-info/top_level.txt
pkgme/backends/cmake/build_depends
pkgme/backends/cmake/depends
pkgme/backends/cmake/package_name
pkgme/backends/cmake/want
pkgme/backends/dummy/package_name
pkgme/backends/dummy/version
pkgme/backends/dummy/want
pkgme/backends/python/all_info
pkgme/backends/python/want
pkgme/backends/vala/architecture
pkgme/backends/vala/build_depends
pkgme/backends/vala/buildsystem
pkgme/backends/vala/depends
pkgme/backends/vala/homepage
pkgme/backends/vala/package_name
pkgme/backends/vala/want
pkgme/bin/__init__.py
pkgme/bin/main.py
pkgme/distutils_command/__init__.py
pkgme/distutils_command/pkgme_info.py
pkgme/helpers/pkgme_autoconf_config
pkgme/helpers/pkgme_autoconf_description
pkgme/helpers/pkgme_autoconf_homepage
pkgme/helpers/pkgme_autoconf_initfield
pkgme/helpers/pkgme_autoconf_maintainer
pkgme/helpers/pkgme_autoconf_package_name
pkgme/templates/control
pkgme/templates/copyright
pkgme/templates/desktop
pkgme/templates/rules
pkgme/templates/test_dummy
pkgme/tests/__init__.py
pkgme/tests/test_api.py
pkgme/tests/test_backend.py
pkgme/tests/test_debuild.py
pkgme/tests/test_distutils_command.py
pkgme/tests/test_info_elements.py
pkgme/tests/test_main.py
pkgme/tests/test_package_files.py
pkgme/tests/test_project_info.py
pkgme/tests/test_python_backend.py
pkgme/tests/test_run_script.py
pkgme/tests/test_script.py
pkgme/tests/test_template_file.py
pkgme/tests/test_testing.py
pkgme/tests/test_trace.py
pkgme/tests/test_upload.py
pkgme/tests/test_vala_backend.py
pkgme/tests/test_write.py