Metadata-Version: 1.0
Name: pkgme
Version: 0.4.3
Summary: =====
Home-page: http://launchpad.net/pkgme
Author: pkgme developers
Author-email: pkgme-devs@lists.launchpad.net
License: GPLv3
Platform: UNKNOWN
